		[
			{
				"id": "20210802",
				"name": "NIMS",
				"exp": "2022-01-01",
				"quantity": "200",
				"price": "35"
			},
			{
				"id": "2021123",
				"name": "Paracetamol",
				"exp": "2023-08-01",
				"quantity": "175",
				"price": "27"
			},
			{
				"id": "2021127",
				"name": "Zubsolv",
				"exp": "2023-08-20",
				"quantity": "60",
				"price": "31"
			},
			{
				"id": "2021122",
				"name": "Xanax",
				"exp": "2023-08-17",
				"quantity": "179",
				"price": "54"
			},
			{
				"id": "2021121",
				"name": "Wellbutrin",
				"exp": "2023-08-20",
				"quantity": "53",
				"price": "31"
			},
			{
				"id": "2021121",
				"name": "Viagra",
				"exp": "2023-08-25",
				"quantity": "128",
				"price": "40"
			},
			{
				"id": "20211210",
				"name": "Trazodone",
				"exp": "2023-08-25",
				"quantity": "68",
				"price": "35"
			},
			{
				"id": "2021127",
				"name": "Tramadol",
				"exp": "2023-08-18",
				"quantity": "78",
				"price": "58"
			},
			{
				"id": "2021127",
				"name": "Sublocade",
				"exp": "2023-08-6",
				"quantity": "188",
				"price": "22"
			},
			{
				"id": "2021123",
				"name": "Rybelsus",
				"exp": "2023-08-23",
				"quantity": "74",
				"price": "57"
			},
			{
				"id": "2021123",
				"name": "Probuphine",
				"exp": "2023-08-10",
				"quantity": "",
				"price": "11"
			},
			{
				"id": "2021125",
				"name": "Prednisone",
				"exp": "2023-08-19",
				"quantity": "12",
				"price": "11"
			},
			{
				"id": "2021128",
				"name": "Pantoprazole",
				"exp": "2023-08-18",
				"quantity": "38",
				"price": "18"
			},
			{
				"id": "20211210",
				"name": "Ozempic",
				"exp": "2023-08-10",
				"quantity": "146",
				"price": "28"
			},
			{
				"id": "20211210",
				"name": "Otezla",
				"exp": "2023-08-27",
				"quantity": "158",
				"price": "34"
			},
			{
				"id": "2021122",
				"name": "Onpattro",
				"exp": "2023-08-27",
				"quantity": "33",
				"price": "13"
			},
			{
				"id": "2021129",
				"name": "Omeprazole",
				"exp": "2023-08-1",
				"quantity": "69",
				"price": "10"
			},
			{
				"id": "2021126",
				"name": "Naproxen",
				"exp": "2023-08-16",
				"quantity": "192",
				"price": "13"
			},
			{
				"id": "2021123",
				"name": "Naltrexone",
				"exp": "2023-08-22",
				"quantity": "68",
				"price": "38"
			},
			{
				"id": "2021123",
				"name": "Naloxone",
				"exp": "2023-08-25",
				"quantity": "75",
				"price": "51"
			},
			{
				"id": "2021127",
				"name": "Metoprolol",
				"exp": "2023-08-23",
				"quantity": "180",
				"price": "26"
			},
			{
				"id": "2021121",
				"name": "Methotrexate",
				"exp": "2023-08-10",
				"quantity": "154",
				"price": "33"
			},
			{
				"id": "2021123",
				"name": "Methadone",
				"exp": "2023-08-16",
				"quantity": "15",
				"price": "14"
			},
			{
				"id": "2021125",
				"name": "Metformin",
				"exp": "2023-08-27",
				"quantity": "166",
				"price": "13"
			},
			{
				"id": "2021127",
				"name": "Meloxicam",
				"exp": "2023-08-22",
				"quantity": "21",
				"price": "32"
			},
			{
				"id": "2021121",
				"name": "Melatonin",
				"exp": "2023-08-24",
				"quantity": "67",
				"price": "16"
			},
			{
				"id": "2021123",
				"name": "Lyrica",
				"exp": "2023-08-8",
				"quantity": "196",
				"price": "32"
			},
			{
				"id": "2021129",
				"name": "Loratadine",
				"exp": "2023-08-16",
				"quantity": "166",
				"price": "16"
			},
			{
				"id": "2021125",
				"name": "Lofexidine",
				"exp": "2023-08-1",
				"quantity": "14",
				"price": "40"
			},
			{
				"id": "2021121",
				"name": "Lisinopril",
				"exp": "2023-08-20",
				"quantity": "138",
				"price": "12"
			},
			{
				"id": "2021121",
				"name": "Lexapro",
				"exp": "2023-08-1",
				"quantity": "4",
				"price": "58"
			},
			{
				"id": "2021123",
				"name": "Kevzara",
				"exp": "2023-08-21",
				"quantity": "179",
				"price": "12"
			},
			{
				"id": "2021128",
				"name": "Jardiance",
				"exp": "2023-08-6",
				"quantity": "132",
				"price": "30"
			},
			{
				"id": "2021128",
				"name": "Januvia",
				"exp": "2023-08-21",
				"quantity": "186",
				"price": "53"
			},
			{
				"id": "2021125",
				"name": "Invokana",
				"exp": "2023-08-15",
				"quantity": "181",
				"price": "56"
			},
			{
				"id": "2021125",
				"name": "Imbruvica",
				"exp": "2023-08-9",
				"quantity": "152",
				"price": "51"
			},
			{
				"id": "2021124",
				"name": "Ibuprofen",
				"exp": "2023-08-7",
				"quantity": "55",
				"price": "34"
			},
			{
				"id": "2021126",
				"name": "Hydroxychloroquine",
				"exp": "2023-08-28",
				"quantity": "46",
				"price": "55"
			},
			{
				"id": "2021123",
				"name": "Hydrochlorothiazide",
				"exp": "2023-08-8",
				"quantity": "42",
				"price": "33"
			},
			{
				"id": "2021122",
				"name": "Humira",
				"exp": "2023-08-3",
				"quantity": "65",
				"price": "22"
			},
			{
				"id": "2021122",
				"name": "Gabapentin",
				"exp": "2023-08-14",
				"quantity": "46",
				"price": "12"
			},
			{
				"id": "2021124",
				"name": "Gilenya",
				"exp": "2023-08-18",
				"quantity": "106",
				"price": "10"
			},
			{
				"id": "2021126",
				"name": "Fentanyl",
				"exp": "2023-08-23",
				"quantity": "72",
				"price": "26"
			},
			{
				"id": "2021122",
				"name": "Doxycycline",
				"exp": "2023-08-21",
				"quantity": "89",
				"price": "56"
			},
			{
				"id": "2021125",
				"name": "Cyclobenzaprine",
				"exp": "2023-08-12",
				"quantity": "95",
				"price": "55"
			},
			{
				"id": "20211210",
				"name": "Clonazepam",
				"exp": "2023-08-1",
				"quantity": "78",
				"price": "17"
			},
			{
				"id": "2021122",
				"name": "Buprenorphine",
				"exp": "2023-08-17",
				"quantity": "82",
				"price": "12"
			},
			{
				"id": "2021122",
				"name": "Ciprofloxacin",
				"exp": "2023-08-10",
				"quantity": "171",
				"price": "33"
			},
			{
				"id": "2021121",
				"name": "Entresto",
				"exp": "2023-08-18",
				"quantity": "60",
				"price": "11"
			},
			{
				"id": "2021125",
				"name": "Citalopram",
				"exp": "2023-08-26",
				"quantity": "38",
				"price": "32"
			}
		]